{
  "project_info": {
    "project_number": "105655490920",
    "project_id": "handy-handy",
    "storage_bucket": "handy-handy.appspot.com"
  },
  "client": [
    {
      "client_info": {
        "mobilesdk_app_id": "1:105655490920:android:955bef5f09e27f3d671edd",
        "android_client_info": {
          "package_name": "ir.misaghpour.handy_dandy_app"
        }
      },
      "oauth_client": [
        {
          "client_id": "105655490920-6j0vrc50oflavfjsd6ih782tfhhs7bjk.apps.googleusercontent.com",
          "client_type": 3
        }
      ],
      "api_key": [
        {
          "current_key": "AIzaSyCK22OJoGQwLWaPVIW5kgbBxMoHh6gJTvU"
        }
      ],
      "services": {
        "appinvite_service": {
          "other_platform_oauth_client": [
            {
              "client_id": "105655490920-6j0vrc50oflavfjsd6ih782tfhhs7bjk.apps.googleusercontent.com",
              "client_type": 3
            }
          ]
        }
      }
    }
  ],
  "configuration_version": "1"
}